defense_predictor/__init__.py
defense_predictor/core.py
defense_predictor/downloads.py
defense_predictor-1.0.1.dist-info/LICENSE
defense_predictor-1.0.1.dist-info/METADATA
defense_predictor-1.0.1.dist-info/WHEEL
defense_predictor-1.0.1.dist-info/entry_points.txt
defense_predictor-1.0.1.dist-info/RECORD
