Metadata-Version: 2.1
Name: defense-predictor
Version: 1.0.1
Summary: Python module for running Defense Predictor, a machine learning model to predict antiphage defense systems
License: MIT
Author: peterdeweirdt
Author-email: petedeweirdt@gmail.com
Requires-Python: >=3.10,<4.0
Classifier: License :: OSI Approved :: MIT License
Classifier: Programming Language :: Python :: 3
Classifier: Programming Language :: Python :: 3.10
Classifier: Programming Language :: Python :: 3.11
Classifier: Programming Language :: Python :: 3.12
Classifier: Programming Language :: Python :: 3.13
Requires-Dist: fair-esm (>=2.0.0,<3.0.0)
Requires-Dist: joblib (>=1.4.2,<2.0.0)
Requires-Dist: lightgbm (>=4.5.0,<5.0.0)
Requires-Dist: numpy (>=2.1.2,<3.0.0)
Requires-Dist: pandas (>=2.2.3,<3.0.0)
Requires-Dist: requests (>=2.32.3,<3.0.0)
Requires-Dist: scikit-learn (>=1.5.2,<2.0.0)
Requires-Dist: torch (>=2.5.1,<2.6.0)
Requires-Dist: tqdm (>=4.67.0,<5.0.0)
